diffcp-1.1.8.dist-info/RECORD
diffcp-1.1.8.dist-info/WHEEL
diffcp-1.1.8.dist-info/METADATA
diffcp-1.1.8.dist-info/licenses/LICENSE
diffcp/cones.py
diffcp/__init__.py
diffcp/utils.py
diffcp/cone_program.py
diffcp/_diffcp.cpython-310-darwin.so
