Metadata-Version: 2.2
Name: diffcp
Version: 1.1.8
Summary: A library to compute gradients for convex optimization problems
License: Apache License, Version 2.0
Project-URL: Homepage, https://github.com/cvxgrp/diffcp/
Requires-Python: >=3.10
Requires-Dist: cvxpy>=1.6.3
Requires-Dist: threadpoolctl>=1.1
Provides-Extra: test
Requires-Dist: clarabel>=0.5.1; extra == "test"
Requires-Dist: scs>=3.0.0; extra == "test"
Requires-Dist: pytest>=8.3.5; extra == "test"
Requires-Dist: ecos>=2.0.10; extra == "test"
